[
  {
    "id": "p1",
    "nombre": "Cuaderno A4 Tapa Dura",
    "precio": 3000,
    "categoria": "Librería",
    "imagen": "https://raw.githubusercontent.com/ludmilasolutions/mgv/e01dbf42648802d4bcfc92a077a3b728880b9181/assets/uploads/2025/08/1755986714593_whatsapp-image-2025-08-11-at-2.57.30-pm.jpeg",
    "descripcion": "96 hojas rayadas, tapa dura."
  },
  {
    "id": "p2",
    "nombre": "Lapicera Gel Multicolor",
    "precio": 1200,
    "categoria": "Librería",
    "imagen": "https://images.unsplash.com/photo-1526318472351-c75fcf070305?w=800&q=80",
    "descripcion": "Trazo suave, colores intensos."
  },
  {
    "id": "p3",
    "nombre": "Taza personalizada",
    "precio": 6000,
    "categoria": "Regalería",
    "imagen": "https://images.unsplash.com/photo-1517705008128-361805f42e86?w=800&q=80",
    "descripcion": "Cerámica, impresión full color."
  },
  {
    "id": "p4",
    "nombre": "Almohadón estampado",
    "precio": 7500,
    "categoria": "Regalería",
    "imagen": "https://images.unsplash.com/photo-1494438639946-1ebd1d20bf85?w=800&q=80",
    "descripcion": "45x45 cm, súper suave."
  },
  {
    "id": "p5",
    "nombre": "Set marcadores flúo x6",
    "precio": 2800,
    "categoria": "Ofertas",
    "imagen": "https://images.unsplash.com/photo-1584380931276-32aebf3a4906?w=800&q=80",
    "descripcion": "Alta visibilidad y durabilidad."
  }
]